{
    "newsItems": [
        {
            "date": "2021/11/03",
            "url": "https://www.pref.shizuoka.jp/kinkyu/covid-19-tyuumokujouhou.html",
            "text": "本日県内で5名の陽性者が確認されました"
        },
        {
            "date": "2021/10/29",
            "url": "https://www.pref.shizuoka.jp/kinkyu/covid-19-keikailevel.html",
            "text": "現在の警戒レベルを更新しました"
        },
        {
            "date": "2021/10/15",
            "url": "https://www.pref.shizuoka.jp/kinkyu/covid-19-kinkyujitai2.html",
            "text": "令和３年10月15日以降の静岡県の対応を掲載しました"
        },
        {
            "date": "2021/09/28",
            "url": "https://www.pref.shizuoka.jp/kinkyu/covid-19-tijikomennto.html",
            "text": "川勝知事からのメッセージを更新しました"
        },
        {
            "date": "2021/09/07",
            "url": "https://fujinokuni-yado.com/entry/",
            "text": "宿泊施設向け「ふじのくに安全・安心認証制度」「宿泊施設感染防止対策強化事業費補助金」の情報を掲載しました"
        },
        {
            "date": "2021/08/16",
            "url": "https://www.pref.shizuoka.jp/sangyou/sa-550/chushokigyotoouenkin.html",
            "text": "中小企業等応援金の概要を掲載しました"
        },
        {
            "date": "2021/07/14",
            "url": "https://www.youtube.com/watch?v=KkS6zpOjxXg",
            "text": "マウリシオ・デ・ソウザ氏の御協力によりMonica & Freind の「手洗いソング」を掲載しました"
        }
    ]
}